{
    "playlists": [
      {
        "playlistID": 0,
        "playlist_name": "Chill Vibes",
        "playlist_author": "Alice",
        "playlist_art": "",
        "songs": [
          {
          "title": "Die with a Smile",
          "author": "Lady Gaga & Bruno Mars",
          "duration": "4:11",
          "art": ""
        },
        {
          "title": "Handlebars (feat. Dua Lipa)",
          "author": "JENNIE",
          "duration": "3:05",
          "art": ""
        },
        {
          "title": "luther (with SZA)",
          "author": "Kendrick Lamar",
          "duration": "2:58",
          "art": ""
        }]
      },
      {
        "playlistID": 1,
        "playlist_name": "Workout Hits",
        "playlist_author": "Bob",
        "playlist_art": "",
        "songs": [
          {
          "title": "Die with a Smile",
          "author": "Lady Gaga & Bruno Mars",
          "duration": "4:11",
          "art": ""
        },
        {
          "title": "Handlebars (feat. Dua Lipa)",
          "author": "JENNIE",
          "duration": "3:05",
          "art": ""
        },
        {
          "title": "luther (with SZA)",
          "author": "Kendrick Lamar",
          "duration": "2:58",
          "art": ""
        }]
      },
      {
        "playlistID": 2,
        "playlist_name": "Throwback Classics",
        "playlist_author": "Charlie",
        "playlist_art": "",
        "songs": [
          {
          "title": "Die with a Smile",
          "author": "Lady Gaga & Bruno Mars",
          "duration": "4:11",
          "art": ""
        },
        {
          "title": "Handlebars (feat. Dua Lipa)",
          "author": "JENNIE",
          "duration": "3:05",
          "art": ""
        },
        {
          "title": "luther (with SZA)",
          "author": "Kendrick Lamar",
          "duration": "2:58",
          "art": ""
        }]
      },
      {
        "playlistID": 3,
        "playlist_name": "Indie Essentials",
        "playlist_author": "Diana",
        "playlist_art": "",
        "songs": [
          {
          "title": "Die with a Smile",
          "author": "Lady Gaga & Bruno Mars",
          "duration": "4:11",
          "art": ""
        },
        {
          "title": "Handlebars (feat. Dua Lipa)",
          "author": "JENNIE",
          "duration": "3:05",
          "art": ""
        },
        {
          "title": "luther (with SZA)",
          "author": "Kendrick Lamar",
          "duration": "2:58",
          "art": ""
        }]
      },
      {
        "playlistID": 4,
        "playlist_name": "Jazz Lounge",
        "playlist_author": "Eli",
        "playlist_art": "",
        "songs": [
          {
          "title": "Die with a Smile",
          "author": "Lady Gaga & Bruno Mars",
          "duration": "4:11",
          "art": ""
        },
        {
          "title": "Handlebars (feat. Dua Lipa)",
          "author": "JENNIE",
          "duration": "3:05",
          "art": ""
        },
        {
          "title": "luther (with SZA)",
          "author": "Kendrick Lamar",
          "duration": "2:58",
          "art": ""
        }]
      },
      {
        "playlistID": 5,
        "playlist_name": "Party Starters",
        "playlist_author": "Faye",
        "playlist_art": "",
        "songs": [
          {
          "title": "Die with a Smile",
          "author": "Lady Gaga & Bruno Mars",
          "duration": "4:11",
          "art": ""
        },
        {
          "title": "Handlebars (feat. Dua Lipa)",
          "author": "JENNIE",
          "duration": "3:05",
          "art": ""
        },
        {
          "title": "luther (with SZA)",
          "author": "Kendrick Lamar",
          "duration": "2:58",
          "art": ""
        }]
      },
      {
        "playlistID": 6,
        "playlist_name": "Late Night Drive",
        "playlist_author": "Gabe",
        "playlist_art": "",
        "songs": [
          {
          "title": "Die with a Smile",
          "author": "Lady Gaga & Bruno Mars",
          "duration": "4:11",
          "art": ""
        },
        {
          "title": "Handlebars (feat. Dua Lipa)",
          "author": "JENNIE",
          "duration": "3:05",
          "art": ""
        },
        {
          "title": "luther (with SZA)",
          "author": "Kendrick Lamar",
          "duration": "2:58",
          "art": ""
        }]
      },
      {
        "playlistID": 7,
        "playlist_name": "Focus Mode",
        "playlist_author": "Hannah",
        "playlist_art": "",
        "songs": [
          {
          "title": "Die with a Smile",
          "author": "Lady Gaga & Bruno Mars",
          "duration": "4:11",
          "art": ""
        },
        {
          "title": "Handlebars (feat. Dua Lipa)",
          "author": "JENNIE",
          "duration": "3:05",
          "art": ""
        },
        {
          "title": "luther (with SZA)",
          "author": "Kendrick Lamar",
          "duration": "2:58",
          "art": ""
        }]
      }
    ]
  }
